eit_django_utils/.DS_Store
eit_django_utils/__init__.py
eit_django_utils/apps.py
eit_django_utils/context_processors.py
eit_django_utils/models.py
eit_django_utils/urls.py
eit_django_utils/views.py
eit_django_utils/backends/__init__.py
eit_django_utils/backends/custom_auth.py
eit_django_utils/backends/utils.py
eit_django_utils/static/eit_django_utils/css/eit_django_utils.css
eit_django_utils/static/img/.gitignore
eit_django_utils/static/js/eit_django_utils.js
eit_django_utils/templates/eit_django_utils/403.html
eit_django_utils/templates/eit_django_utils/404.html
eit_django_utils/templates/eit_django_utils/500.html
eit_django_utils/templates/eit_django_utils/base.html
eit_django_utils-0.4.4.dist-info/LICENSE
eit_django_utils-0.4.4.dist-info/WHEEL
eit_django_utils-0.4.4.dist-info/METADATA
eit_django_utils-0.4.4.dist-info/RECORD
