Metadata-Version: 2.1
Name: eit_django_utils
Version: 0.4.4
Summary: django utils for eit
Author-email: Daniel Nall <sdnall@ncsu.edu>
Requires-Python: >=3.6
Classifier: License :: OSI Approved :: MIT License
Requires-Dist: Django >=2.2
Requires-Dist: django-hijack <= 2.3.0
Project-URL: Home, https://github.ncsu.edu/EIT/eit_django_utils
